CrypticPhenoImpute/CrypticPhenoImpute.py
CrypticPhenoImpute/__init__.py
CrypticPhenoImpute/__main__.py
CrypticPhenoImpute/Data/HPOTable.txt
CrypticPhenoImpute/Data/ICD10-UKBB_ModelTable.pth
CrypticPhenoImpute/Data/ModelTable.txt
CrypticPhenoImpute/Data/TargetDiseaseCodes.txt
CrypticPhenoImpute-0.0.7.dist-info/LICENSE
CrypticPhenoImpute-0.0.7.dist-info/METADATA
CrypticPhenoImpute-0.0.7.dist-info/WHEEL
CrypticPhenoImpute-0.0.7.dist-info/entry_points.txt
CrypticPhenoImpute-0.0.7.dist-info/top_level.txt
CrypticPhenoImpute-0.0.7.dist-info/RECORD
