Metadata-Version: 2.1
Name: CrypticPhenoImpute
Version: 0.0.7
Summary: Imputes cryptic phenotypes analyzed in Blair et al. into arbitrary clinical datasets.
Home-page: https://github.com/daverblair/CrypticPhenoImpute
Author: David Blair
Author-email: david.blair@ucsf.edu
License: UNKNOWN
Platform: UNKNOWN
Classifier: Programming Language :: Python :: 3
Classifier: License :: OSI Approved :: MIT License
Classifier: Operating System :: OS Independent
Requires-Dist: argparse (>=1.1)
Requires-Dist: numpy (>=1.19.0)
Requires-Dist: pandas (>=1.0.5)
Requires-Dist: statsmodels (>=0.11.1)
Requires-Dist: scipy (>=1.5.2)
Requires-Dist: scikit-learn (==0.22.1)
Requires-Dist: vlpi
Requires-Dist: wget
